LICENSE
pyxvis/__init__.py
pyxvis/features/__init__.py
pyxvis/features/descriptors.py
pyxvis/features/extraction.py
pyxvis/features/selection.py
pyxvis/geometry/__init__.py
pyxvis/geometry/epipolar.py
pyxvis/geometry/projective.py
pyxvis/io/__init__.py
pyxvis/io/data.py
pyxvis/io/gdxraydb.py
pyxvis/io/misc.py
pyxvis/io/plots.py
pyxvis/io/visualization.py
pyxvis/learning/__init__.py
pyxvis/learning/classifiers.py
pyxvis/learning/cnn.py
pyxvis/learning/evaluation.py
pyxvis/learning/gan.py
pyxvis/learning/pretrained.py
pyxvis/learning/transfer.py
pyxvis/processing/__init__.py
pyxvis/processing/helpers/__init__.py
pyxvis/processing/helpers/kfunctions.py
pyxvis/processing/images.py
pyxvis/processing/segmentation.py
pyxvis/simulation/__init__.py
pyxvis/simulation/xsim.py
pyxvis-0.1.0a9.dist-info/LICENSE
pyxvis-0.1.0a9.dist-info/WHEEL
pyxvis-0.1.0a9.dist-info/METADATA
pyxvis-0.1.0a9.dist-info/RECORD
